AUTHORS.rst
CONTRIBUTING.rst
HISTORY.rst
LICENSE
MANIFEST.in
README.rst
setup.cfg
setup.py
distill/__init__.py
distill/cli.py
distill.py.egg-info/PKG-INFO
distill.py.egg-info/SOURCES.txt
distill.py.egg-info/dependency_links.txt
distill.py.egg-info/entry_points.txt
distill.py.egg-info/not-zip-safe
distill.py.egg-info/requires.txt
distill.py.egg-info/top_level.txt
docs/index.rst
tests/__init__.py