Metadata-Version: 1.1
Name: distill.py
Version: 0.0.2
Summary: Doc platform for coder.
Home-page: https://github.com/magizbox/distill.py
Author: Vu Anh
Author-email: brother.rain.1024@gmail.com
License: GNU General Public License v3
Keywords: underthesea
Platform: UNKNOWN
Classifier: Development Status :: 2 - Pre-Alpha
Classifier: Intended Audience :: Developers
Classifier: License :: OSI Approved :: GNU General Public License v3 (GPLv3)
Classifier: Natural Language :: English
Classifier: Programming Language :: Python :: 3.4
